xpubsub/__init__.py
xpubsub/pubsub.py
xpubsub-0.2.0.dist-info/LICENSE
xpubsub-0.2.0.dist-info/WHEEL
xpubsub-0.2.0.dist-info/METADATA
xpubsub-0.2.0.dist-info/RECORD
