Metadata-Version: 2.1
Name: xpubsub
Version: 0.2.0
Summary: Basic PubSub for python app.
Home-page: https://github.com/treborg/xpubsub
License: MIT
Keywords: pubsub,utility,example,education
Author: treborg
Author-email: treborg@atomix.uk
Requires-Python: >=3.10
Classifier: Development Status :: 3 - Alpha
Classifier: License :: OSI Approved :: MIT License
Classifier: Natural Language :: English
Classifier: Programming Language :: Python :: 3
Classifier: Programming Language :: Python :: 3.10
Classifier: Programming Language :: Python :: 3.11
Classifier: Programming Language :: Python :: 3
Classifier: Programming Language :: Python :: 3.10
Classifier: Programming Language :: Python :: 3.11
Classifier: Topic :: Software Development :: Libraries :: Python Modules
Project-URL: Documentation, https://github.com/xpubsub
Project-URL: Repository, https://github.com/treborg/xpubsub
